suguru/__init__.py
suguru/game.py
suguru/solver.py
suguru/suguru.py
suguru-0.0.1.dist-info/entry_points.txt
suguru-0.0.1.dist-info/LICENSE
suguru-0.0.1.dist-info/WHEEL
suguru-0.0.1.dist-info/METADATA
suguru-0.0.1.dist-info/RECORD
