Metadata-Version: 2.1
Name: suguru
Version: 0.0.1
Summary: Suguru library.
Author-email: Roi Gabay <roigby@gmail.com>
Requires-Python: >=3.9
Classifier: Programming Language :: Python :: 3
Classifier: License :: OSI Approved :: MIT License
Classifier: Operating System :: OS Independent
Requires-Dist: black ; extra == "dev"
Requires-Dist: pygame ; extra == "pygame"
Requires-Dist: z3 ; extra == "pygame"
Requires-Dist: pytest ; extra == "test"
Requires-Dist: pytest-cov ; extra == "test"
Requires-Dist: z3 ; extra == "z3"
Project-URL: Bug Tracker, https://github.com/gabay/suguru/issues
Project-URL: Home, https://github.com/gabay/suguru
Provides-Extra: dev
Provides-Extra: pygame
Provides-Extra: test
Provides-Extra: z3
